<?xml version="1.0" encoding="UTF-8"?>
<GenRun Id="synth_1" LaunchPart="xc7a35tcpg236-1" LaunchTime="1653580832">
  <File Type="VDS-TIMING-PB" Name="ROM_timing_summary_synth.pb"/>
  <File Type="VDS-TIMINGSUMMARY" Name="ROM_timing_summary_synth.rpt"/>
  <File Type="RDS-DCP" Name="ROM.dcp"/>
  <File Type="RDS-UTIL-PB" Name="ROM_utilization_synth.pb"/>
  <File Type="RDS-UTIL" Name="ROM_utilization_synth.rpt"/>
  <File Type="RDS-PROPCONSTRS" Name="ROM_drc_synth.rpt"/>
  <File Type="RDS-RDS" Name="ROM.vds"/>
  <File Type="REPORTS-TCL" Name="ROM_reports.tcl"/>
  <File Type="PA-TCL" Name="ROM.tcl"/>
  <FileSet Name="sources" Type="DesignSrcs" RelSrcDir="$PSRCDIR/sources_1">
    <Filter Type="Srcs"/>
    <File Path="$PSRCDIR/sources_1/new/ALU.vhd">
      <FileInfo>
        <Attr Name="ImportPath" Val="$PPRDIR/../../../../compilator/compilator.srcs/sources_1/new/ALU.vhd"/>
        <Attr Name="ImportTime" Val="1649318755"/>
        <Attr Name="UsedIn" Val="synthesis"/>
        <Attr Name="UsedIn" Val="simulation"/>
      </FileInfo>
    </File>
    <File Path="$PSRCDIR/sources_1/new/processor.vhd">
      <FileInfo>
        <Attr Name="ImportPath" Val="$PPRDIR/../../../../compilator/compilator.srcs/sources_1/new/processor.vhd"/>
        <Attr Name="ImportTime" Val="1649315438"/>
        <Attr Name="UsedIn" Val="synthesis"/>
        <Attr Name="UsedIn" Val="simulation"/>
      </FileInfo>
    </File>
    <File Path="$PSRCDIR/sources_1/new/RAM.vhd">
      <FileInfo>
        <Attr Name="ImportPath" Val="$PPRDIR/../../../../compilator/compilator.srcs/sources_1/new/RAM.vhd"/>
        <Attr Name="ImportTime" Val="1652176779"/>
        <Attr Name="UsedIn" Val="synthesis"/>
        <Attr Name="UsedIn" Val="simulation"/>
      </FileInfo>
    </File>
    <File Path="$PSRCDIR/sources_1/new/BANC_REGISTRE.vhd">
      <FileInfo>
        <Attr Name="ImportPath" Val="$PPRDIR/../../../../compilator/compilator.srcs/sources_1/new/BANC_REGISTRE.vhd"/>
        <Attr Name="ImportTime" Val="1649315701"/>
        <Attr Name="UsedIn" Val="synthesis"/>
        <Attr Name="UsedIn" Val="simulation"/>
      </FileInfo>
    </File>
    <File Path="$PPRDIR/../../../../compilator/compilator.srcs/sources_1/new/ROM.vhd">
      <FileInfo>
        <Attr Name="UsedIn" Val="synthesis"/>
        <Attr Name="UsedIn" Val="simulation"/>
      </FileInfo>
    </File>
    <File Path="$PSRCDIR/sources_1/new/Pipeline.vhd">
      <FileInfo>
        <Attr Name="UsedIn" Val="synthesis"/>
        <Attr Name="UsedIn" Val="simulation"/>
      </FileInfo>
    </File>
    <Config>
      <Option Name="DesignMode" Val="RTL"/>
      <Option Name="TopModule" Val="ROM"/>
    </Config>
  </FileSet>
  <FileSet Name="constrs_in" Type="Constrs" RelSrcDir="$PSRCDIR/constrs_1">
    <Filter Type="Constrs"/>
    <Config>
      <Option Name="ConstrsType" Val="XDC"/>
    </Config>
  </FileSet>
  <Strategy Version="1" Minor="2">
    <StratHandle Name="Vivado Synthesis Defaults" Flow="Vivado Synthesis 2018"/>
    <Step Id="synth_design"/>
  </Strategy>
</GenRun>
